uv_trail/__init__.py
uv_trail/py.typed
uv_trail-0.1.0.dist-info/WHEEL
uv_trail-0.1.0.dist-info/METADATA
uv_trail-0.1.0.dist-info/RECORD
