Metadata-Version: 2.3
Name: uv-trail
Version: 0.1.0
Summary: Add your description here
Requires-Dist: matplotlib>=3.10.5
Requires-Dist: numpy>=2.3.2
Requires-Dist: pandas>=2.3.2
Requires-Dist: scikit-learn>=1.7.1
Requires-Dist: scipy>=1.16.1
Requires-Dist: torch>=2.8.0
Requires-Python: >=3.11
